pychunk/__init__.py
pychunk/pychunk.py
pychunk-1.0.0.dist-info/LICENSE
pychunk-1.0.0.dist-info/WHEEL
pychunk-1.0.0.dist-info/METADATA
pychunk-1.0.0.dist-info/RECORD
