Metadata-Version: 2.1
Name: pychunk
Version: 1.0.0
Summary: Chunks an iterator
License: Apache
Author: Bhavani Ravi
Author-email: bhavanicodes@gmail.com
Requires-Python: >=3.8,<4.0
Classifier: License :: Other/Proprietary License
Classifier: Programming Language :: Python :: 3
Classifier: Programming Language :: Python :: 3.8
Classifier: Programming Language :: Python :: 3.9
Classifier: Programming Language :: Python :: 3.10
Classifier: Programming Language :: Python :: 3.11
